theme_153957/.DS_Store
theme_153957/__init__.py
theme_153957/full_menu.py
theme_153957/static/.DS_Store
theme_153957/static/css/normalize.css
theme_153957/static/css/style.css
theme_153957/static/font/.DS_Store
theme_153957/static/font/.htaccess
theme_153957/static/font/Jost-400.woff2
theme_153957/static/font/Jost-700.woff2
theme_153957/static/js/.DS_Store
theme_153957/static/js/gallery.js
theme_153957/templates/album.html
theme_153957/templates/album_list.html
theme_153957/templates/base.html
theme_153957/templates/menu.html
theme_153957/theme.py
153957_theme-7.0.dist-info/licenses/LICENSE
153957_theme-7.0.dist-info/WHEEL
153957_theme-7.0.dist-info/METADATA
153957_theme-7.0.dist-info/RECORD
