Metadata-Version: 2.4
Name: 153957-theme
Version: 7.0
Summary: Theme for sigal generated photo albums
Keywords: photo album,theme,sigal
Author: Arne de Laat
Author-email: Arne de Laat <arne@delaat.net>
License-Expression: MIT
License-File: LICENSE
Classifier: Environment :: Plugins
Classifier: Environment :: Web Environment
Classifier: License :: OSI Approved :: MIT License
Classifier: Programming Language :: Python
Classifier: Programming Language :: Python :: 3
Classifier: Topic :: Text Processing :: Markup :: HTML
Requires-Dist: sigal==2.5
Requires-Dist: mypy==1.17.0 ; extra == 'dev'
Maintainer: Arne de Laat
Maintainer-email: Arne de Laat <arne@delaat.net>
Requires-Python: >=3.13
Project-URL: Repository, https://github.com/153957/153957-theme/
Provides-Extra: dev
